verilog_files/fulladder.v
module fulladder(
    output crry,
    output sum,
    input in1,
    input in2,
    input cin);

assign {crry, sum} = in1+in2+cin;
endmodule

verilog_files/fourbitadder.v
`include "fulladder.v"


module fourbitadder(
    output crry,
    output [3:0]sum,
    input [3:0]in1,
    input [3:0]in2,
    input cin );

wire [2:0]intm;

fulladder fa1(intm[0], sum[0], in1[0], in2[0], cin);
fulladder fa2(intm[1], sum[1], in1[1], in2[1], intm[0]);
fulladder fa3(intm[2], sum[2], in1[2], in2[2], intm[1]);
fulladder fa4(crry, sum[3], in1[3], in2[3], intm[2]);
endmodule

verilog_files/fourbitaddsub.v
`include "fourbitadder.v"

module fourbitaddsub(
    output crry,
    output [3:0]sum,
    input [3:0]in1,
    input [3:0]in2,
    input ctrl ); //If ctrl =1 then sub else add.

    wire [3:0]intm;

    // XOR outputs for the adder.
    xor xor1(intm[0], in2[0], ctrl);
    xor xor2(intm[1], in2[1], ctrl);
    xor xor3(intm[2], in2[2], ctrl);
    xor xor4(intm[3], in2[3], ctrl);

    fourbitadder fba(crry, sum, in1, intm, ctrl);
endmodule

test_bench/fourbitaddsub_tb.v
`include "../verilog_files/fourbitaddsub.v"

module fourbitaddsub_tb;

reg [3:0]in1, in2;
reg ctrl;

wire [3:0]sum;
wire crry;

integer v1, v2;

fourbitaddsub ins1(crry, sum, in1, in2, ctrl);

initial begin
    $dumpfile("fourbitaddsub_dump.vcd");
    $dumpvars(0,ins1);
    $monitor("in1: %b | in2: %b | ctrl: %b || crry: %b | sum: %b",in1, in2, ctrl, crry, sum);
    for (v1 = 4'b0000; v1 < 16; v1=v1+4'b0001) begin
        for (v2 = 4'b0000; v2 < 16; v2=v2+4'b0001) begin
            #10 in1 = v1; in2 = v2; ctrl = 1'b0;
            #10 in1 = v1; in2 = v2; ctrl = 1'b1;
        end
    end
    #10 $finish;
end
endmodule

sim_files/fourbitaddsub_dump.vcd
$date
	Mon Jun 24 16:55:16 2019
$end
$version
	Icarus Verilog
$end
$timescale
	1s
$end
$scope module fourbitaddsub_tb $end
$scope module ins1 $end
$var wire 1 ! ctrl $end
$var wire 4 " in1 [3:0] $end
$var wire 4 # in2 [3:0] $end
$var wire 4 $ sum [3:0] $end
$var wire 4 % intm [3:0] $end
$var wire 1 & crry $end
$scope module fba $end
$var wire 1 ! cin $end
$var wire 4 ' in1 [3:0] $end
$var wire 4 ( in2 [3:0] $end
$var wire 4 ) sum [3:0] $end
$var wire 3 * intm [2:0] $end
$var wire 1 & crry $end
$scope module fa1 $end
$var wire 1 ! cin $end
$var wire 1 + in1 $end
$var wire 1 , in2 $end
$var wire 1 - sum $end
$var wire 1 . crry $end
$upscope $end
$scope module fa2 $end
$var wire 1 / cin $end
$var wire 1 0 in1 $end
$var wire 1 1 in2 $end
$var wire 1 2 sum $end
$var wire 1 3 crry $end
$upscope $end
$scope module fa3 $end
$var wire 1 4 cin $end
$var wire 1 5 in1 $end
$var wire 1 6 in2 $end
$var wire 1 7 sum $end
$var wire 1 8 crry $end
$upscope $end
$scope module fa4 $end
$var wire 1 9 cin $end
$var wire 1 : in1 $end
$var wire 1 ; in2 $end
$var wire 1 < sum $end
$var wire 1 & crry $end
$upscope $end
$upscope $end
$upscope $end
$upscope $end
$enddefinitions $end
#0
$dumpvars
x<
x;
x:
x9
x8
x7
x6
x5
x4
x3
x2
x1
x0
x/
x.
x-
x,
x+
bx *
bx )
bx (
bx '
x&
bx %
bx $
bx #
bx "
x!
$end
#10
0<
0&
09
07
08
04
02
03
0/
b0 $
b0 )
0-
b0 *
0.
0,
01
06
0;
b0 %
b0 (
0+
00
05
0:
0!
b0 #
b0 "
b0 '
#20
1&
19
18
14
13
1/
b111 *
1.
02
07
0<
1,
11
16
1;
b1111 %
b1111 (
b0 $
b0 )
0-
1!
#30
09
04
07
08
0<
0&
03
01
06
0;
0/
b1 %
b1 (
b1 $
b1 )
1-
b0 *
0.
0!
b1 #
#40
0&
09
12
08
04
03
17
1<
0,
11
16
1;
0/
b1110 %
b1110 (
b1111 $
b1111 )
1-
b0 *
0.
1!
#50
07
0<
06
0;
b10 %
b10 (
b10 $
b10 )
0-
0!
b10 #
#60
1/
b1 *
1.
12
17
1<
1,
01
16
1;
b1101 %
b1101 (
b1110 $
b1110 )
0-
1!
#70
07
0<
11
06
0;
0/
b11 %
b11 (
b11 $
b11 )
1-
b0 *
0.
0!
b11 #
#80
02
17
1<
0,
01
16
1;
0/
b1100 %
b1100 (
b1101 $
b1101 )
1-
b0 *
0.
1!
#90
0<
0;
b100 %
b100 (
b100 $
b100 )
0-
0!
b100 #
#100
14
13
1/
b11 *
1.
02
17
1<
1,
11
06
1;
b1011 %
b1011 (
b1100 $
b1100 )
0-
1!
#110
09
04
17
08
0<
03
01
16
0;
0/
b101 %
b101 (
b101 $
b101 )
1-
b0 *
0.
0!
b101 #
#120
12
04
03
07
1<
0,
11
06
1;
0/
b1010 %
b1010 (
b1011 $
b1011 )
1-
b0 *
0.
1!
#130
17
0<
16
0;
b110 %
b110 (
b110 $
b110 )
0-
0!
b110 #
#140
1/
b1 *
1.
12
07
1<
1,
01
06
1;
b1001 %
b1001 (
b1010 $
b1010 )
0-
1!
#150
17
0<
11
16
0;
0/
b111 %
b111 (
b111 $
b111 )
1-
b0 *
0.
0!
b111 #
#160
02
07
1<
0,
01
06
1;
0/
b1000 %
b1000 (
b1001 $
b1001 )
1-
b0 *
0.
1!
#170
b1000 $
b1000 )
0-
0!
b1000 #
#180
19
18
14
13
1/
b111 *
1.
02
07
1<
1,
11
16
0;
b111 %
b111 (
b1000 $
b1000 )
0-
1!
#190
09
04
07
08
1<
0&
03
01
06
1;
0/
b1001 %
b1001 (
b1001 $
b1001 )
1-
b0 *
0.
0!
b1001 #
#200
09
12
08
04
03
17
0<
0,
11
16
0;
0/
b110 %
b110 (
b111 $
b111 )
1-
b0 *
0.
1!
#210
07
1<
06
1;
b1010 %
b1010 (
b1010 $
b1010 )
0-
0!
b1010 #
#220
1/
b1 *
1.
12
17
0<
1,
01
16
0;
b101 %
b101 (
b110 $
b110 )
0-
1!
#230
07
1<
11
06
1;
0/
b1011 %
b1011 (
b1011 $
b1011 )
1-
b0 *
0.
0!
b1011 #
#240
02
17
0<
0,
01
16
0;
0/
b100 %
b100 (
b101 $
b101 )
1-
b0 *
0.
1!
#250
1<
1;
b1100 %
b1100 (
b1100 $
b1100 )
0-
0!
b1100 #
#260
14
13
1/
b11 *
1.
02
17
0<
1,
11
06
0;
b11 %
b11 (
b100 $
b100 )
0-
1!
#270
0&
09
04
17
08
1<
03
01
16
1;
0/
b1101 %
b1101 (
b1101 $
b1101 )
1-
b0 *
0.
0!
b1101 #
#280
12
04
03
07
0<
0,
11
06
0;
0/
b10 %
b10 (
b11 $
b11 )
1-
b0 *
0.
1!
#290
17
1<
16
1;
b1110 %
b1110 (
b1110 $
b1110 )
0-
0!
b1110 #
#300
1/
b1 *
1.
12
07
0<
1,
01
06
0;
b1 %
b1 (
b10 $
b10 )
0-
1!
#310
17
1<
11
16
1;
0/
b1111 %
b1111 (
b1111 $
b1111 )
1-
b0 *
0.
0!
b1111 #
#320
02
07
0<
0,
01
06
0;
0/
b0 %
b0 (
b1 $
b1 )
1-
b0 *
0.
1!
#330
1+
0!
b0 #
b1 "
b1 '
#340
1&
19
18
14
13
07
0<
1,
11
16
1;
1/
b1111 %
b1111 (
b1 $
b1 )
1-
b111 *
1.
1!
#350
04
09
12
03
07
b1 *
08
0<
0&
01
06
0;
b1 %
b1 (
b10 $
b10 )
0-
0!
b1 #
#360
1&
19
18
14
02
b111 *
13
07
0<
0,
11
16
1;
b1110 %
b1110 (
b0 $
b0 )
0-
1!
#370
09
04
07
08
0<
0&
12
03
06
0;
0/
b10 %
b10 (
b11 $
b11 )
1-
b0 *
0.
0!
b10 #
#380
17
1<
1,
01
16
1;
1/
b1101 %
b1101 (
b1111 $
b1111 )
1-
b1 *
1.
1!
#390
14
02
b11 *
13
17
0<
11
06
0;
b11 %
b11 (
b100 $
b100 )
0-
0!
b11 #
#400
0&
04
09
12
03
17
b1 *
08
1<
0,
01
16
1;
b1100 %
b1100 (
b1110 $
b1110 )
0-
1!
#410
0<
02
0;
0/
b100 %
b100 (
b101 $
b101 )
1-
b0 *
0.
0!
b100 #
#420
14
13
17
1<
1,
11
06
1;
1/
b1011 %
b1011 (
b1101 $
b1101 )
1-
b11 *
1.
1!
#430
04
09
12
03
17
b1 *
08
0<
01
16
0;
b101 %
b101 (
b110 $
b110 )
0-
0!
b101 #
#440
14
02
b11 *
13
17
1<
0,
11
06
1;
b1010 %
b1010 (
b1100 $
b1100 )
0-
1!
#450
09
04
17
08
0<
12
03
16
0;
0/
b110 %
b110 (
b111 $
b111 )
1-
b0 *
0.
0!
b110 #
#460
07
1<
1,
01
06
1;
1/
b1001 %
b1001 (
b1011 $
b1011 )
1-
b1 *
1.
1!
#470
19
18
14
02
b111 *
13
07
1<
11
16
0;
b111 %
b111 (
b1000 $
b1000 )
0-
0!
b111 #
#480
04
09
12
03
07
b1 *
08
1<
0&
0,
01
06
1;
b1000 %
b1000 (
b1010 $
b1010 )
0-
1!
#490
02
0/
b1001 $
b1001 )
1-
b0 *
0.
0!
b1000 #
#500
19
18
14
13
07
1<
1,
11
16
0;
1/
b111 %
b111 (
b1001 $
b1001 )
1-
b111 *
1.
1!
#510
04
09
12
03
07
b1 *
08
1<
0&
01
06
1;
b1001 %
b1001 (
b1010 $
b1010 )
0-
0!
b1001 #
#520
19
18
14
02
b111 *
13
07
1<
0,
11
16
0;
b110 %
b110 (
b1000 $
b1000 )
0-
1!
#530
09
04
07
08
1<
0&
12
03
06
1;
0/
b1010 %
b1010 (
b1011 $
b1011 )
1-
b0 *
0.
0!
b1010 #
#540
17
0<
1,
01
16
0;
1/
b101 %
b101 (
b111 $
b111 )
1-
b1 *
1.
1!
#550
14
02
b11 *
13
17
1<
11
06
1;
b1011 %
b1011 (
b1100 $
b1100 )
0-
0!
b1011 #
#560
04
09
12
03
17
b1 *
08
0<
0,
01
16
0;
b100 %
b100 (
b110 $
b110 )
0-
1!
#570
1<
02
1;
0/
b1100 %
b1100 (
b1101 $
b1101 )
1-
b0 *
0.
0!
b1100 #
#580
14
13
17
0<
1,
11
06
0;
1/
b11 %
b11 (
b101 $
b101 )
1-
b11 *
1.
1!
#590
0&
04
09
12
03
17
b1 *
08
1<
01
16
1;
b1101 %
b1101 (
b1110 $
b1110 )
0-
0!
b1101 #
#600
14
02
b11 *
13
17
0<
0,
11
06
0;
b10 %
b10 (
b100 $
b100 )
0-
1!
#610
0&
09
04
17
08
1<
12
03
16
1;
0/
b1110 %
b1110 (
b1111 $
b1111 )
1-
b0 *
0.
0!
b1110 #
#620
07
0<
1,
01
06
0;
1/
b1 %
b1 (
b11 $
b11 )
1-
b1 *
1.
1!
#630
1&
19
18
14
02
b111 *
13
07
0<
11
16
1;
b1111 %
b1111 (
b0 $
b0 )
0-
0!
b1111 #
#640
04
09
12
03
07
b1 *
08
0<
0&
0,
01
06
0;
b0 %
b0 (
b10 $
b10 )
0-
1!
#650
07
04
0/
b10 $
b10 )
12
03
b0 *
0.
0+
10
0!
b0 #
b10 "
b10 '
#660
1&
19
18
1/
14
1.
12
b111 *
13
07
0<
1,
11
16
1;
b1111 %
b1111 (
b10 $
b10 )
0-
1!
#670
04
09
03
07
08
0<
0&
01
06
0;
0/
b1 %
b1 (
b11 $
b11 )
1-
b0 *
0.
0!
b1 #
#680
1&
19
02
18
14
07
0<
13
0,
11
16
1;
0/
b1110 %
b1110 (
b1 $
b1 )
1-
b110 *
0.
1!
#690
09
17
b10 *
08
0<
0&
06
0;
b10 %
b10 (
b100 $
b100 )
0-
0!
b10 #
#700
1&
1/
14
19
1.
02
13
07
b111 *
18
0<
1,
01
16
1;
b1101 %
b1101 (
b0 $
b0 )
0-
1!
#710
09
17
08
0<
0&
11
06
0;
0/
b11 %
b11 (
b101 $
b101 )
1-
b10 *
0.
0!
b11 #
#720
04
12
03
0&
09
17
08
1<
0,
01
16
1;
0/
b1100 %
b1100 (
b1111 $
b1111 )
1-
b0 *
0.
1!
#730
0<
0;
b100 %
b100 (
b110 $
b110 )
0-
0!
b100 #
#740
1/
14
1.
12
b11 *
13
17
1<
1,
11
06
1;
b1011 %
b1011 (
b1110 $
b1110 )
0-
1!
#750
04
09
03
17
08
0<
01
16
0;
0/
b101 %
b101 (
b111 $
b111 )
1-
b0 *
0.
0!
b101 #
#760
02
14
17
1<
13
0,
11
06
1;
0/
b1010 %
b1010 (
b1101 $
b1101 )
1-
b10 *
0.
1!
#770
19
07
b110 *
18
1<
16
0;
b110 %
b110 (
b1000 $
b1000 )
0-
0!
b110 #
#780
1/
14
09
1.
02
13
17
b11 *
08
1<
0&
1,
01
06
1;
b1001 %
b1001 (
b1100 $
b1100 )
0-
1!
#790
19
07
18
1<
11
16
0;
0/
b111 %
b111 (
b1001 $
b1001 )
1-
b110 *
0.
0!
b111 #
#800
04
12
03
09
07
08
1<
0&
0,
01
06
1;
0/
b1000 %
b1000 (
b1011 $
b1011 )
1-
b0 *
0.
1!
#810
b1010 $
b1010 )
0-
0!
b1000 #
#820
19
18
1/
14
1.
12
b111 *
13
07
1<
1,
11
16
0;
b111 %
b111 (
b1010 $
b1010 )
0-
1!
#830
04
09
03
07
08
1<
0&
01
06
1;
0/
b1001 %
b1001 (
b1011 $
b1011 )
1-
b0 *
0.
0!
b1001 #
#840
19
02
18
14
07
1<
13
0,
11
16
0;
0/
b110 %
b110 (
b1001 $
b1001 )
1-
b110 *
0.
1!
#850
09
17
b10 *
08
1<
0&
06
1;
b1010 %
b1010 (
b1100 $
b1100 )
0-
0!
b1010 #
#860
1/
14
19
1.
02
13
07
b111 *
18
1<
1,
01
16
0;
b101 %
b101 (
b1000 $
b1000 )
0-
1!
#870
09
17
08
1<
0&
11
06
1;
0/
b1011 %
b1011 (
b1101 $
b1101 )
1-
b10 *
0.
0!
b1011 #
#880
04
12
03
09
17
08
0<
0,
01
16
0;
0/
b100 %
b100 (
b111 $
b111 )
1-
b0 *
0.
1!
#890
1<
1;
b1100 %
b1100 (
b1110 $
b1110 )
0-
0!
b1100 #
#900
1/
14
1.
12
b11 *
13
17
0<
1,
11
06
0;
b11 %
b11 (
b110 $
b110 )
0-
1!
#910
0&
04
09
03
17
08
1<
01
16
1;
0/
b1101 %
b1101 (
b1111 $
b1111 )
1-
b0 *
0.
0!
b1101 #
#920
02
14
17
0<
13
0,
11
06
0;
0/
b10 %
b10 (
b101 $
b101 )
1-
b10 *
0.
1!
#930
1&
19
07
b110 *
18
0<
16
1;
b1110 %
b1110 (
b0 $
b0 )
0-
0!
b1110 #
#940
1/
14
09
1.
02
13
17
b11 *
08
0<
0&
1,
01
06
0;
b1 %
b1 (
b100 $
b100 )
0-
1!
#950
1&
19
07
18
0<
11
16
1;
0/
b1111 %
b1111 (
b1 $
b1 )
1-
b110 *
0.
0!
b1111 #
#960
04
12
03
09
07
08
0<
0&
0,
01
06
0;
0/
b0 %
b0 (
b11 $
b11 )
1-
b0 *
0.
1!
#970
1+
0!
b0 #
b11 "
b11 '
#980
1&
19
18
14
07
0<
13
1,
11
16
1;
1/
b1111 %
b1111 (
b11 $
b11 )
1-
b111 *
1.
1!
#990
09
02
17
b11 *
08
0<
0&
01
06
0;
b1 %
b1 (
b100 $
b100 )
0-
0!
b1 #
#1000
1&
19
12
07
b111 *
18
0<
0,
11
16
1;
b1110 %
b1110 (
b10 $
b10 )
0-
1!
#1010
09
17
08
0<
0&
02
06
0;
0/
b10 %
b10 (
b101 $
b101 )
1-
b10 *
0.
0!
b10 #
#1020
1&
19
07
18
0<
1,
01
16
1;
1/
b1101 %
b1101 (
b1 $
b1 )
1-
b111 *
1.
1!
#1030
09
12
17
b11 *
08
0<
0&
11
06
0;
b11 %
b11 (
b110 $
b110 )
0-
0!
b11 #
#1040
1&
19
02
07
b111 *
18
0<
0,
01
16
1;
b1100 %
b1100 (
b0 $
b0 )
0-
1!
#1050
09
17
08
04
0<
0&
12
03
0;
0/
b100 %
b100 (
b111 $
b111 )
1-
b0 *
0.
0!
b100 #
#1060
14
17
1<
13
1,
11
06
1;
1/
b1011 %
b1011 (
b1111 $
b1111 )
1-
b11 *
1.
1!
#1070
19
02
07
b111 *
18
1<
01
16
0;
b101 %
b101 (
b1000 $
b1000 )
0-
0!
b101 #
#1080
09
12
17
b11 *
08
1<
0&
0,
11
06
1;
b1010 %
b1010 (
b1110 $
b1110 )
0-
1!
#1090
19
07
18
1<
02
16
0;
0/
b110 %
b110 (
b1001 $
b1001 )
1-
b110 *
0.
0!
b110 #
#1100
09
17
08
1<
0&
1,
01
06
1;
1/
b1001 %
b1001 (
b1101 $
b1101 )
1-
b11 *
1.
1!
#1110
19
12
07
b111 *
18
1<
11
16
0;
b111 %
b111 (
b1010 $
b1010 )
0-
0!
b111 #
#1120
09
02
17
b11 *
08
1<
0&
0,
01
06
1;
b1000 %
b1000 (
b1100 $
b1100 )
0-
1!
#1130
07
04
12
03
0/
b1011 $
b1011 )
1-
b0 *
0.
0!
b1000 #
#1140
19
18
14
07
1<
13
1,
11
16
0;
1/
b111 %
b111 (
b1011 $
b1011 )
1-
b111 *
1.
1!
#1150
09
02
17
b11 *
08
1<
0&
01
06
1;
b1001 %
b1001 (
b1100 $
b1100 )
0-
0!
b1001 #
#1160
19
12
07
b111 *
18
1<
0,
11
16
0;
b110 %
b110 (
b1010 $
b1010 )
0-
1!
#1170
09
17
08
1<
0&
02
06
1;
0/
b1010 %
b1010 (
b1101 $
b1101 )
1-
b10 *
0.
0!
b1010 #
#1180
19
07
18
1<
1,
01
16
0;
1/
b101 %
b101 (
b1001 $
b1001 )
1-
b111 *
1.
1!
#1190
09
12
17
b11 *
08
1<
0&
11
06
1;
b1011 %
b1011 (
b1110 $
b1110 )
0-
0!
b1011 #
#1200
19
02
07
b111 *
18
1<
0,
01
16
0;
b100 %
b100 (
b1000 $
b1000 )
0-
1!
#1210
09
17
08
04
1<
0&
12
03
1;
0/
b1100 %
b1100 (
b1111 $
b1111 )
1-
b0 *
0.
0!
b1100 #
#1220
14
17
0<
13
1,
11
06
0;
1/
b11 %
b11 (
b111 $
b111 )
1-
b11 *
1.
1!
#1230
1&
19
02
07
b111 *
18
0<
01
16
1;
b1101 %
b1101 (
b0 $
b0 )
0-
0!
b1101 #
#1240
09
12
17
b11 *
08
0<
0&
0,
11
06
0;
b10 %
b10 (
b110 $
b110 )
0-
1!
#1250
1&
19
07
18
0<
02
16
1;
0/
b1110 %
b1110 (
b1 $
b1 )
1-
b110 *
0.
0!
b1110 #
#1260
09
17
08
0<
0&
1,
01
06
0;
1/
b1 %
b1 (
b101 $
b101 )
1-
b11 *
1.
1!
#1270
1&
19
12
07
b111 *
18
0<
11
16
1;
b1111 %
b1111 (
b10 $
b10 )
0-
0!
b1111 #
#1280
09
02
17
b11 *
08
0<
0&
0,
01
06
0;
b0 %
b0 (
b100 $
b100 )
0-
1!
#1290
0<
04
09
0/
02
03
b100 $
b100 )
17
08
b0 *
0.
0+
00
15
0!
b0 #
b100 "
b100 '
#1300
14
13
1&
1/
19
1.
02
17
b111 *
18
0<
1,
11
16
1;
b1111 %
b1111 (
b100 $
b100 )
0-
1!
#1310
09
08
04
17
0<
0&
03
01
06
0;
0/
b1 %
b1 (
b101 $
b101 )
1-
b0 *
0.
0!
b1 #
#1320
12
1&
04
19
03
07
18
0<
0,
11
16
1;
0/
b1110 %
b1110 (
b11 $
b11 )
1-
b100 *
0.
1!
#1330
09
17
b0 *
08
0<
0&
06
0;
b10 %
b10 (
b110 $
b110 )
0-
0!
b10 #
#1340
1&
1/
19
1.
12
07
b101 *
18
0<
1,
01
16
1;
b1101 %
b1101 (
b10 $
b10 )
0-
1!
#1350
09
17
08
0<
0&
11
06
0;
0/
b11 %
b11 (
b111 $
b111 )
1-
b0 *
0.
0!
b11 #
#1360
02
1&
19
07
18
0<
0,
01
16
1;
0/
b1100 %
b1100 (
b1 $
b1 )
1-
b100 *
0.
1!
#1370
1<
0&
0;
b100 %
b100 (
b1000 $
b1000 )
0-
0!
b100 #
#1380
14
13
1/
19
1.
02
07
b111 *
18
0<
1&
1,
11
06
1;
b1011 %
b1011 (
b0 $
b0 )
0-
1!
#1390
04
07
1<
0&
03
01
16
0;
0/
b101 %
b101 (
b1001 $
b1001 )
1-
b100 *
0.
0!
b101 #
#1400
12
04
09
03
17
08
1<
0&
0,
11
06
1;
0/
b1010 %
b1010 (
b1111 $
b1111 )
1-
b0 *
0.
1!
#1410
19
07
b100 *
18
1<
16
0;
b110 %
b110 (
b1010 $
b1010 )
0-
0!
b110 #
#1420
1/
09
1.
12
17
b1 *
08
1<
0&
1,
01
06
1;
b1001 %
b1001 (
b1110 $
b1110 )
0-
1!
#1430
19
07
18
1<
11
16
0;
0/
b111 %
b111 (
b1011 $
b1011 )
1-
b100 *
0.
0!
b111 #
#1440
02
09
17
08
1<
0&
0,
01
06
1;
0/
b1000 %
b1000 (
b1101 $
b1101 )
1-
b0 *
0.
1!
#1450
b1100 $
b1100 )
0-
0!
b1000 #
#1460
14
13
1/
19
1.
02
17
b111 *
18
1<
1,
11
16
0;
b111 %
b111 (
b1100 $
b1100 )
0-
1!
#1470
09
08
04
17
1<
0&
03
01
06
1;
0/
b1001 %
b1001 (
b1101 $
b1101 )
1-
b0 *
0.
0!
b1001 #
#1480
12
04
19
03
07
18
1<
0,
11
16
0;
0/
b110 %
b110 (
b1011 $
b1011 )
1-
b100 *
0.
1!
#1490
09
17
b0 *
08
1<
0&
06
1;
b1010 %
b1010 (
b1110 $
b1110 )
0-
0!
b1010 #
#1500
1/
19
1.
12
07
b101 *
18
1<
1,
01
16
0;
b101 %
b101 (
b1010 $
b1010 )
0-
1!
#1510
09
17
08
1<
0&
11
06
1;
0/
b1011 %
b1011 (
b1111 $
b1111 )
1-
b0 *
0.
0!
b1011 #
#1520
02
19
07
18
1<
0,
01
16
0;
0/
b100 %
b100 (
b1001 $
b1001 )
1-
b100 *
0.
1!
#1530
0<
1&
1;
b1100 %
b1100 (
b0 $
b0 )
0-
0!
b1100 #
#1540
14
13
1/
19
1.
02
07
b111 *
18
1<
0&
1,
11
06
0;
b11 %
b11 (
b1000 $
b1000 )
0-
1!
#1550
04
07
0<
1&
03
01
16
1;
0/
b1101 %
b1101 (
b1 $
b1 )
1-
b100 *
0.
0!
b1101 #
#1560
12
04
09
03
17
08
0<
0&
0,
11
06
0;
0/
b10 %
b10 (
b111 $
b111 )
1-
b0 *
0.
1!
#1570
1&
19
07
b100 *
18
0<
16
1;
b1110 %
b1110 (
b10 $
b10 )
0-
0!
b1110 #
#1580
1/
09
1.
12
17
b1 *
08
0<
0&
1,
01
06
0;
b1 %
b1 (
b110 $
b110 )
0-
1!
#1590
1&
19
07
18
0<
11
16
1;
0/
b1111 %
b1111 (
b11 $
b11 )
1-
b100 *
0.
0!
b1111 #
#1600
02
09
17
08
0<
0&
0,
01
06
0;
0/
b0 %
b0 (
b101 $
b101 )
1-
b0 *
0.
1!
#1610
1+
0!
b0 #
b101 "
b101 '
#1620
1&
14
19
13
17
18
0<
1,
11
16
1;
1/
b1111 %
b1111 (
b101 $
b101 )
1-
b111 *
1.
1!
#1630
09
08
04
12
b1 *
03
17
0<
0&
01
06
0;
b1 %
b1 (
b110 $
b110 )
0-
0!
b1 #
#1640
1&
14
19
02
13
17
b111 *
18
0<
0,
11
16
1;
b1110 %
b1110 (
b100 $
b100 )
0-
1!
#1650
09
08
04
17
0<
0&
12
03
06
0;
0/
b10 %
b10 (
b111 $
b111 )
1-
b0 *
0.
0!
b10 #
#1660
1&
19
07
18
0<
1,
01
16
1;
1/
b1101 %
b1101 (
b11 $
b11 )
1-
b101 *
1.
1!
#1670
14
19
02
13
07
b111 *
18
1<
0&
11
06
0;
b11 %
b11 (
b1000 $
b1000 )
0-
0!
b11 #
#1680
04
12
b101 *
03
07
0<
1&
0,
01
16
1;
b1100 %
b1100 (
b10 $
b10 )
0-
1!
#1690
1<
0&
02
0;
0/
b100 %
b100 (
b1001 $
b1001 )
1-
b100 *
0.
0!
b100 #
#1700
14
19
13
07
18
0<
1&
1,
11
06
1;
1/
b1011 %
b1011 (
b1 $
b1 )
1-
b111 *
1.
1!
#1710
04
12
b101 *
03
07
1<
0&
01
16
0;
b101 %
b101 (
b1010 $
b1010 )
0-
0!
b101 #
#1720
14
19
02
13
07
b111 *
18
0<
1&
0,
11
06
1;
b1010 %
b1010 (
b0 $
b0 )
0-
1!
#1730
04
07
1<
0&
12
03
16
0;
0/
b110 %
b110 (
b1011 $
b1011 )
1-
b100 *
0.
0!
b110 #
#1740
09
17
08
1<
0&
1,
01
06
1;
1/
b1001 %
b1001 (
b1111 $
b1111 )
1-
b1 *
1.
1!
#1750
14
19
02
13
17
b111 *
18
1<
11
16
0;
b111 %
b111 (
b1100 $
b1100 )
0-
0!
b111 #
#1760
09
08
04
12
b1 *
03
17
1<
0&
0,
01
06
1;
b1000 %
b1000 (
b1110 $
b1110 )
0-
1!
#1770
02
0/
b1101 $
b1101 )
1-
b0 *
0.
0!
b1000 #
#1780
14
19
13
17
18
1<
1,
11
16
0;
1/
b111 %
b111 (
b1101 $
b1101 )
1-
b111 *
1.
1!
#1790
09
08
04
12
b1 *
03
17
1<
0&
01
06
1;
b1001 %
b1001 (
b1110 $
b1110 )
0-
0!
b1001 #
#1800
14
19
02
13
17
b111 *
18
1<
0,
11
16
0;
b110 %
b110 (
b1100 $
b1100 )
0-
1!
#1810
09
08
04
17
1<
0&
12
03
06
1;
0/
b1010 %
b1010 (
b1111 $
b1111 )
1-
b0 *
0.
0!
b1010 #
#1820
19
07
18
1<
1,
01
16
0;
1/
b101 %
b101 (
b1011 $
b1011 )
1-
b101 *
1.
1!
#1830
14
19
02
13
07
b111 *
18
0<
1&
11
06
1;
b1011 %
b1011 (
b0 $
b0 )
0-
0!
b1011 #
#1840
04
12
b101 *
03
07
1<
0&
0,
01
16
0;
b100 %
b100 (
b1010 $
b1010 )
0-
1!
#1850
0<
1&
02
1;
0/
b1100 %
b1100 (
b1 $
b1 )
1-
b100 *
0.
0!
b1100 #
#1860
14
19
13
07
18
1<
0&
1,
11
06
0;
1/
b11 %
b11 (
b1001 $
b1001 )
1-
b111 *
1.
1!
#1870
04
12
b101 *
03
07
0<
1&
01
16
1;
b1101 %
b1101 (
b10 $
b10 )
0-
0!
b1101 #
#1880
14
19
02
13
07
b111 *
18
1<
0&
0,
11
06
0;
b10 %
b10 (
b1000 $
b1000 )
0-
1!
#1890
04
07
0<
1&
12
03
16
1;
0/
b1110 %
b1110 (
b11 $
b11 )
1-
b100 *
0.
0!
b1110 #
#1900
09
17
08
0<
0&
1,
01
06
0;
1/
b1 %
b1 (
b111 $
b111 )
1-
b1 *
1.
1!
#1910
1&
14
19
02
13
17
b111 *
18
0<
11
16
1;
b1111 %
b1111 (
b100 $
b100 )
0-
0!
b1111 #
#1920
09
08
04
12
b1 *
03
17
0<
0&
0,
01
06
0;
b0 %
b0 (
b110 $
b110 )
0-
1!
#1930
0<
09
17
08
04
0/
b110 $
b110 )
12
03
b0 *
0.
0+
10
0!
b0 #
b110 "
b110 '
#1940
1&
1/
14
19
1.
12
13
17
b111 *
18
0<
1,
11
16
1;
b1111 %
b1111 (
b110 $
b110 )
0-
1!
#1950
09
08
04
03
17
0<
0&
01
06
0;
0/
b1 %
b1 (
b111 $
b111 )
1-
b0 *
0.
0!
b1 #
#1960
02
1&
19
14
17
18
0<
13
0,
11
16
1;
0/
b1110 %
b1110 (
b101 $
b101 )
1-
b110 *
0.
1!
#1970
07
1<
0&
06
0;
b10 %
b10 (
b1000 $
b1000 )
0-
0!
b10 #
#1980
1/
14
1.
02
b111 *
13
17
0<
1&
1,
01
16
1;
b1101 %
b1101 (
b100 $
b100 )
0-
1!
#1990
07
1<
0&
11
06
0;
0/
b11 %
b11 (
b1001 $
b1001 )
1-
b110 *
0.
0!
b11 #
#2000
04
12
03
07
0<
1&
0,
01
16
1;
0/
b1100 %
b1100 (
b11 $
b11 )
1-
b100 *
0.
1!
#2010
1<
0&
0;
b100 %
b100 (
b1010 $
b1010 )
0-
0!
b100 #
#2020
1/
14
19
1.
12
13
07
b111 *
18
0<
1&
1,
11
06
1;
b1011 %
b1011 (
b10 $
b10 )
0-
1!
#2030
04
03
07
1<
0&
01
16
0;
0/
b101 %
b101 (
b1011 $
b1011 )
1-
b100 *
0.
0!
b101 #
#2040
02
19
14
07
18
0<
1&
13
0,
11
06
1;
0/
b1010 %
b1010 (
b1 $
b1 )
1-
b110 *
0.
1!
#2050
17
1<
0&
16
0;
b110 %
b110 (
b1100 $
b1100 )
0-
0!
b110 #
#2060
19
18
1/
14
1.
02
b111 *
13
07
0<
1&
1,
01
06
1;
b1001 %
b1001 (
b0 $
b0 )
0-
1!
#2070
17
1<
0&
11
16
0;
0/
b111 %
b111 (
b1101 $
b1101 )
1-
b110 *
0.
0!
b111 #
#2080
09
08
04
12
03
17
1<
0&
0,
01
06
1;
0/
b1000 %
b1000 (
b1111 $
b1111 )
1-
b0 *
0.
1!
#2090
b1110 $
b1110 )
0-
0!
b1000 #
#2100
1/
14
19
1.
12
13
17
b111 *
18
1<
1,
11
16
0;
b111 %
b111 (
b1110 $
b1110 )
0-
1!
#2110
09
08
04
03
17
1<
0&
01
06
1;
0/
b1001 %
b1001 (
b1111 $
b1111 )
1-
b0 *
0.
0!
b1001 #
#2120
02
19
14
17
18
1<
13
0,
11
16
0;
0/
b110 %
b110 (
b1101 $
b1101 )
1-
b110 *
0.
1!
