verilog_files/fulladder.v
module fulladder(
    output crry,
    output sum,
    input in1,
    input in2,
    input cin);

assign {crry, sum} = in1+in2+cin;
endmodule

verilog_files/fourbitadder.v
`include "fulladder.v"


module fourbitadder(
    output crry,
    output [3:0]sum,
    input [3:0]in1,
    input [3:0]in2,
    input cin );

wire [2:0]intm;

fulladder fa1(intm[0], sum[0], in1[0], in2[0], cin);
fulladder fa2(intm[1], sum[1], in1[1], in2[1], intm[0]);
fulladder fa3(intm[2], sum[2], in1[2], in2[2], intm[1]);
fulladder fa4(crry, sum[3], in1[3], in2[3], intm[2]);
endmodule

test_bench/fourbitadder_tb.v
`include "../verilog_files/fourbitadder.v"

module fourbitadder_tb;

reg [3:0]val1, val2;
reg cin;
wire [3:0]sum;
wire crry;

integer v1, v2, v3;


fourbitadder ins1(crry, sum, val1, val2, cin);

initial begin
    $dumpfile("fourbitadder_dump.vcd");
    $dumpvars(0,ins1);
    $monitor("val1: %b | val2: %b | cin: %b || crry: %b | sum: %b",val1, val2, cin, crry, sum);
    for (v1 = 4'b0000; v1 < 16; v1=v1+4'b0001) begin
        for (v2 = 4'b0000; v2 < 16; v2=v2+4'b0001) begin
            #10 val1 = v1; val2 = v2; cin = 1'b0;
            #10 val1 = v1; val2 = v2; cin = 1'b1;
        end
    end
    #10 $finish;
end
endmodule

test_bench/fourbitadder_dump.vcd
$date
	Mon Jun 24 16:36:05 2019
$end
$version
	Icarus Verilog
$end
$timescale
	1s
$end
$scope module fourbitadder_tb $end
$scope module ins1 $end
$var wire 1 ! cin $end
$var wire 4 " in1 [3:0] $end
$var wire 4 # in2 [3:0] $end
$var wire 4 $ sum [3:0] $end
$var wire 3 % intm [2:0] $end
$var wire 1 & crry $end
$scope module fa1 $end
$var wire 1 ! cin $end
$var wire 1 ' in1 $end
$var wire 1 ( in2 $end
$var wire 1 ) sum $end
$var wire 1 * crry $end
$upscope $end
$scope module fa2 $end
$var wire 1 + cin $end
$var wire 1 , in1 $end
$var wire 1 - in2 $end
$var wire 1 . sum $end
$var wire 1 / crry $end
$upscope $end
$scope module fa3 $end
$var wire 1 0 cin $end
$var wire 1 1 in1 $end
$var wire 1 2 in2 $end
$var wire 1 3 sum $end
$var wire 1 4 crry $end
$upscope $end
$scope module fa4 $end
$var wire 1 5 cin $end
$var wire 1 6 in1 $end
$var wire 1 7 in2 $end
$var wire 1 8 sum $end
$var wire 1 & crry $end
$upscope $end
$upscope $end
$upscope $end
$enddefinitions $end
#0
$dumpvars
x8
x7
x6
x5
x4
x3
x2
x1
x0
x/
x.
x-
x,
x+
x*
x)
x(
x'
x&
bx %
bx $
bx #
bx "
x!
$end
#10
08
0&
05
03
04
00
0.
0/
0+
b0 $
0)
b0 %
0*
0(
0-
02
07
0'
0,
01
06
0!
b0 #
b0 "
#20
b1 $
1)
1!
#30
1(
0!
b1 #
#40
1.
1+
b10 $
0)
b1 %
1*
1!
#50
03
00
0+
b10 $
1.
0/
b0 %
0*
0(
1-
0!
b10 #
#60
b11 $
1)
1!
#70
1(
0!
b11 #
#80
13
10
0.
1/
1+
b100 $
0)
b11 %
1*
1!
#90
08
00
05
0+
0.
0/
b100 $
13
04
b0 %
0*
0(
0-
12
0!
b100 #
#100
b101 $
1)
1!
#110
1(
0!
b101 #
#120
1.
1+
b110 $
0)
b1 %
1*
1!
#130
08
05
13
04
00
0+
b110 $
1.
0/
b0 %
0*
0(
1-
0!
b110 #
#140
b111 $
1)
1!
#150
1(
0!
b111 #
#160
18
15
03
14
10
0.
1/
1+
b1000 $
0)
b111 %
1*
1!
#170
00
05
0+
0.
0/
03
04
b1000 $
18
0&
b0 %
0*
0(
0-
02
17
0!
b1000 #
#180
b1001 $
1)
1!
#190
1(
0!
b1001 #
#200
1.
1+
b1010 $
0)
b1 %
1*
1!
#210
03
00
0+
b1010 $
1.
0/
b0 %
0*
0(
1-
0!
b1010 #
#220
b1011 $
1)
1!
#230
1(
0!
b1011 #
#240
13
10
0.
1/
1+
b1100 $
0)
b11 %
1*
1!
#250
18
0&
00
05
0+
0.
0/
b1100 $
13
04
b0 %
0*
0(
0-
12
0!
b1100 #
#260
b1101 $
1)
1!
#270
1(
0!
b1101 #
#280
1.
1+
b1110 $
0)
b1 %
1*
1!
#290
18
0&
05
13
04
00
0+
b1110 $
1.
0/
b0 %
0*
0(
1-
0!
b1110 #
#300
b1111 $
1)
1!
#310
1(
0!
b1111 #
#320
08
1&
15
03
14
10
0.
1/
1+
b0 $
0)
b111 %
1*
1!
#330
00
05
0+
0.
0/
03
04
08
0&
b1 $
1)
b0 %
0*
0(
0-
02
07
1'
0!
b0 #
b1 "
#340
1.
1+
b10 $
0)
b1 %
1*
1!
#350
1(
0!
b1 #
#360
b11 $
1)
1!
#370
03
0+
00
0*
b11 $
1.
b0 %
0/
0(
1-
0!
b10 #
#380
13
10
0.
1/
1+
b100 $
0)
b11 %
1*
1!
#390
1(
0!
b11 #
#400
b101 $
1)
1!
#410
08
0+
00
05
0*
0.
0/
b101 $
13
b0 %
04
0(
0-
12
0!
b100 #
#420
1.
1+
b110 $
0)
b1 %
1*
1!
#430
1(
0!
b101 #
#440
b111 $
1)
1!
#450
08
05
13
04
0+
00
0*
b111 $
1.
b0 %
0/
0(
1-
0!
b110 #
#460
18
15
03
14
10
0.
1/
1+
b1000 $
0)
b111 %
1*
1!
#470
1(
0!
b111 #
#480
b1001 $
1)
1!
#490
0+
00
05
0*
0.
0/
03
b0 %
04
b1001 $
18
0&
0(
0-
02
17
0!
b1000 #
#500
1.
1+
b1010 $
0)
b1 %
1*
1!
#510
1(
0!
b1001 #
#520
b1011 $
1)
1!
#530
03
0+
00
0*
b1011 $
1.
b0 %
0/
0(
1-
0!
b1010 #
#540
13
10
0.
1/
1+
b1100 $
0)
b11 %
1*
1!
#550
1(
0!
b1011 #
#560
b1101 $
1)
1!
#570
18
0&
0+
00
05
0*
0.
0/
b1101 $
13
b0 %
04
0(
0-
12
0!
b1100 #
#580
1.
1+
b1110 $
0)
b1 %
1*
1!
#590
1(
0!
b1101 #
#600
b1111 $
1)
1!
#610
18
0&
05
13
04
0+
00
0*
b1111 $
1.
b0 %
0/
0(
1-
0!
b1110 #
#620
08
1&
15
03
14
10
0.
1/
1+
b0 $
0)
b111 %
1*
1!
#630
1(
0!
b1111 #
#640
b1 $
1)
1!
#650
00
1.
0/
05
0+
03
04
08
0&
b0 %
0*
b10 $
0)
0(
0-
02
07
0'
1,
0!
b0 #
b10 "
#660
b11 $
1)
1!
#670
1(
0!
b1 #
#680
13
10
0.
1/
1+
b100 $
0)
b11 %
1*
1!
#690
0+
b100 $
0.
b10 %
0*
0(
1-
0!
b10 #
#700
b101 $
1)
1!
#710
1(
0!
b11 #
#720
1.
1+
b110 $
0)
b11 %
1*
1!
#730
00
08
0/
05
0+
1.
b110 $
13
04
b0 %
0*
0(
0-
12
0!
b100 #
#740
b111 $
1)
1!
#750
1(
0!
b101 #
#760
18
15
03
14
10
0.
1/
1+
b1000 $
0)
b111 %
1*
1!
#770
0+
b1000 $
0.
b110 %
0*
0(
1-
0!
b110 #
#780
b1001 $
1)
1!
#790
1(
0!
b111 #
#800
1.
1+
b1010 $
0)
b111 %
1*
1!
#810
00
0/
05
0+
1.
03
04
b1010 $
18
0&
b0 %
0*
0(
0-
02
17
0!
b1000 #
#820
b1011 $
1)
1!
#830
1(
0!
b1001 #
#840
13
10
0.
1/
1+
b1100 $
0)
b11 %
1*
1!
#850
0+
b1100 $
0.
b10 %
0*
0(
1-
0!
b1010 #
#860
b1101 $
1)
1!
#870
1(
0!
b1011 #
#880
1.
1+
b1110 $
0)
b11 %
1*
1!
#890
00
18
0&
0/
05
0+
1.
b1110 $
13
04
b0 %
0*
0(
0-
12
0!
b1100 #
#900
b1111 $
1)
1!
#910
1(
0!
b1101 #
#920
08
1&
15
03
14
10
0.
1/
1+
b0 $
0)
b111 %
1*
1!
#930
0+
b0 $
0.
b110 %
0*
0(
1-
0!
b1110 #
#940
b1 $
1)
1!
#950
1(
0!
b1111 #
#960
1.
1+
b10 $
0)
b111 %
1*
1!
#970
00
0/
05
0+
1.
03
04
08
0&
b11 $
1)
b0 %
0*
0(
0-
02
07
1'
0!
b0 #
b11 "
#980
13
10
0.
1/
1+
b100 $
0)
b11 %
1*
1!
#990
1(
0!
b1 #
#1000
b101 $
1)
1!
#1010
0+
b10 %
0*
b101 $
0.
0(
1-
0!
b10 #
#1020
1.
1+
b110 $
0)
b11 %
1*
1!
#1030
1(
0!
b11 #
#1040
b111 $
1)
1!
#1050
00
0/
08
0+
05
0*
1.
b111 $
13
b0 %
04
0(
0-
12
0!
b100 #
#1060
18
15
03
14
10
0.
1/
1+
b1000 $
0)
b111 %
1*
1!
#1070
1(
0!
b101 #
#1080
b1001 $
1)
1!
#1090
0+
b110 %
0*
b1001 $
0.
0(
1-
0!
b110 #
#1100
1.
1+
b1010 $
0)
b111 %
1*
1!
#1110
1(
0!
b111 #
#1120
b1011 $
1)
1!
#1130
00
0/
0+
05
0*
1.
03
b0 %
04
b1011 $
18
0&
0(
0-
02
17
0!
b1000 #
#1140
13
10
0.
1/
1+
b1100 $
0)
b11 %
1*
1!
#1150
1(
0!
b1001 #
#1160
b1101 $
1)
1!
#1170
0+
b10 %
0*
b1101 $
0.
0(
1-
0!
b1010 #
#1180
1.
1+
b1110 $
0)
b11 %
1*
1!
#1190
1(
0!
b1011 #
#1200
b1111 $
1)
1!
#1210
00
0/
18
0&
0+
05
0*
1.
b1111 $
13
b0 %
04
0(
0-
12
0!
b1100 #
#1220
08
1&
15
03
14
10
0.
1/
1+
b0 $
0)
b111 %
1*
1!
#1230
1(
0!
b1101 #
#1240
b1 $
1)
1!
#1250
0+
b110 %
0*
b1 $
0.
0(
1-
0!
b1110 #
#1260
1.
1+
b10 $
0)
b111 %
1*
1!
#1270
1(
0!
b1111 #
#1280
b11 $
1)
1!
#1290
05
13
04
0.
00
0+
0/
08
0&
b0 %
0*
b100 $
0)
0(
0-
02
07
0'
0,
11
0!
b0 #
b100 "
#1300
b101 $
1)
1!
#1310
1(
0!
b1 #
#1320
1.
1+
b110 $
0)
b1 %
1*
1!
#1330
08
05
13
04
00
0+
b110 $
1.
0/
b0 %
0*
0(
1-
0!
b10 #
#1340
b111 $
1)
1!
#1350
1(
0!
b11 #
#1360
18
15
03
14
10
0.
1/
1+
b1000 $
0)
b111 %
1*
1!
#1370
00
0+
0.
0/
b1000 $
03
b100 %
0*
0(
0-
12
0!
b100 #
#1380
b1001 $
1)
1!
#1390
1(
0!
b101 #
#1400
1.
1+
b1010 $
0)
b101 %
1*
1!
#1410
03
00
0+
b1010 $
1.
0/
b100 %
0*
0(
1-
0!
b110 #
#1420
b1011 $
1)
1!
#1430
1(
0!
b111 #
#1440
13
10
0.
1/
1+
b1100 $
0)
b111 %
1*
1!
#1450
05
04
00
0+
0.
0/
13
b1100 $
18
0&
b0 %
0*
0(
0-
02
17
0!
b1000 #
#1460
b1101 $
1)
1!
#1470
1(
0!
b1001 #
#1480
1.
1+
b1110 $
0)
b1 %
1*
1!
#1490
18
0&
05
13
04
00
0+
b1110 $
1.
0/
b0 %
0*
0(
1-
0!
b1010 #
#1500
b1111 $
1)
1!
#1510
1(
0!
b1011 #
#1520
08
1&
15
03
14
10
0.
1/
1+
b0 $
0)
b111 %
1*
1!
#1530
00
0+
0.
0/
b0 $
03
b100 %
0*
0(
0-
12
0!
b1100 #
#1540
b1 $
1)
1!
#1550
1(
0!
b1101 #
#1560
1.
1+
b10 $
0)
b101 %
1*
1!
#1570
03
00
0+
b10 $
1.
0/
b100 %
0*
0(
1-
0!
b1110 #
#1580
b11 $
1)
1!
#1590
1(
0!
b1111 #
#1600
13
10
0.
1/
1+
b100 $
0)
b111 %
1*
1!
#1610
05
04
00
0+
0.
0/
13
08
0&
b101 $
1)
b0 %
0*
0(
0-
02
07
1'
0!
b0 #
b101 "
#1620
1.
1+
b110 $
0)
b1 %
1*
1!
#1630
1(
0!
b1 #
#1640
b111 $
1)
1!
#1650
08
05
13
04
0+
00
0*
b111 $
1.
b0 %
0/
0(
1-
0!
b10 #
#1660
18
15
03
14
10
0.
1/
1+
b1000 $
0)
b111 %
1*
1!
#1670
1(
0!
b11 #
#1680
b1001 $
1)
1!
#1690
0+
00
0*
0.
b100 %
0/
b1001 $
03
0(
0-
12
0!
b100 #
#1700
1.
1+
b1010 $
0)
b101 %
1*
1!
#1710
1(
0!
b101 #
#1720
b1011 $
1)
1!
#1730
03
0+
00
0*
b1011 $
1.
b100 %
0/
0(
1-
0!
b110 #
#1740
13
10
0.
1/
1+
b1100 $
0)
b111 %
1*
1!
#1750
1(
0!
b111 #
#1760
b1101 $
1)
1!
#1770
05
04
0+
00
0*
0.
b0 %
0/
13
b1101 $
18
0&
0(
0-
02
17
0!
b1000 #
#1780
1.
1+
b1110 $
0)
b1 %
1*
1!
#1790
1(
0!
b1001 #
#1800
b1111 $
1)
1!
#1810
18
0&
05
13
04
0+
00
0*
b1111 $
1.
b0 %
0/
0(
1-
0!
b1010 #
#1820
08
1&
15
03
14
10
0.
1/
1+
b0 $
0)
b111 %
1*
1!
#1830
1(
0!
b1011 #
#1840
b1 $
1)
1!
#1850
0+
00
0*
0.
b100 %
0/
b1 $
03
0(
0-
12
0!
b1100 #
#1860
1.
1+
b10 $
0)
b101 %
1*
1!
#1870
1(
0!
b1101 #
#1880
b11 $
1)
1!
#1890
03
0+
00
0*
b11 $
1.
b100 %
0/
0(
1-
0!
b1110 #
#1900
13
10
0.
1/
1+
b100 $
0)
b111 %
1*
1!
#1910
1(
0!
b1111 #
#1920
b101 $
1)
1!
#1930
05
04
00
1.
0/
0+
13
08
0&
b0 %
0*
b110 $
0)
0(
0-
02
07
0'
1,
0!
b0 #
b110 "
#1940
b111 $
1)
1!
#1950
1(
0!
b1 #
#1960
18
15
03
14
10
0.
1/
1+
b1000 $
0)
b111 %
1*
1!
#1970
0+
b1000 $
0.
b110 %
0*
0(
1-
0!
b10 #
#1980
b1001 $
1)
1!
#1990
1(
0!
b11 #
#2000
1.
1+
b1010 $
0)
b111 %
1*
1!
#2010
00
0/
0+
1.
b1010 $
03
b100 %
0*
0(
0-
12
0!
b100 #
#2020
b1011 $
1)
1!
#2030
1(
0!
b101 #
#2040
13
10
0.
1/
1+
b1100 $
0)
b111 %
1*
1!
#2050
0+
b1100 $
0.
b110 %
0*
0(
1-
0!
b110 #
#2060
b1101 $
1)
1!
#2070
1(
0!
b111 #
#2080
1.
1+
b1110 $
0)
b111 %
1*
1!
#2090
05
04
00
0/
0+
1.
13
b1110 $
18
0&
b0 %
0*
0(
0-
02
17
0!
b1000 #
#2100
b1111 $
1)
1!
#2110
1(
0!
b1001 #
#2120
08
1&
15
03
14
10
0.
1/
1+
b0 $
0)
b111 %
1*
1!
#2130
0+
b0 $
0.
b110 %
0*
0(
1-
0!
b1010 #
#2140
b1 $
1)
1!
#2150
1(
0!
b1011 #
#2160
1.
1+
b10 $
0)
b111 %
1*
1!
#2170
00
0/
0+
1.
b10 $
03
b100 %
0*
0(
0-
12
0!
b1100 #
#2180
b11 $
1)
1!
#2190
1(
0!
b1101 #
#2200
13
10
0.
1/
1+
b100 $
0)
b111 %
1*
1!
#2210
0+
b100 $
0.
b110 %
0*
0(
1-
0!
b1110 #
#2220
b101 $
1)
1!
#2230
1(
0!
b1111 #
#2240
1.
1+
b110 $
0)
b111 %
1*
1!
#2250
05
04
00
0/
0+
1.
13
08
0&
b111 $
1)
b0 %
0*
0(
0-
02
07
1'
0!
b0 #
b111 "
#2260
18
15
03
14
10
0.
1/
1+
b1000 $
0)
b111 %
1*
1!
#2270
1(
0!
b1 #
#2280
b1001 $
1)
1!
#2290
0+
b110 %
0*
b1001 $
0.
0(
1-
0!
b10 #
#2300
1.
1+
b1010 $
0)
b111 %
1*
1!
#2310
1(
0!
b11 #
#2320
b1011 $
1)
1!
#2330
00
0/
0+
b100 %
0*
1.
b1011 $
03
0(
0-
12
0!
b100 #
#2340
13
10
0.
1/
1+
b1100 $
0)
b111 %
1*
1!
#2350
1(
0!
b101 #
#2360
b1101 $
1)
1!
#2370
0+
b110 %
0*
b1101 $
0.
0(
1-
0!
b110 #
#2380
1.
1+
b1110 $
0)
b111 %
1*
1!
#2390
1(
0!
b111 #
#2400
b1111 $
1)
1!
#2410
05
04
00
0/
0+
b0 %
0*
1.
13
b1111 $
18
0&
0(
0-
02
17
0!
b1000 #
#2420
08
1&
15
03
14
10
0.
1/
1+
b0 $
0)
b111 %
1*
1!
#2430
1(
0!
b1001 #
#2440
b1 $
1)
1!
#2450
0+
b110 %
0*
b1 $
0.
0(
1-
0!
b1010 #
#2460
1.
1+
b10 $
0)
b111 %
1*
1!
#2470
1(
0!
b1011 #
#2480
b11 $
1)
1!
#2490
00
0/
0+
b100 %
0*
1.
b11 $
03
0(
0-
12
0!
b1100 #
#2500
13
10
0.
1/
1+
b100 $
0)
b111 %
1*
1!
#2510
1(
0!
b1101 #
#2520
b101 $
1)
1!
#2530
0+
b110 %
0*
b101 $
0.
0(
1-
0!
b1110 #
#2540
1.
1+
b110 $
0)
b111 %
1*
1!
#2550
1(
0!
b1111 #
#2560
b111 $
1)
1!
#2570
03
18
0&
0.
00
05
0+
0/
04
b0 %
0*
b1000 $
0)
0(
0-
02
07
0'
0,
01
16
0!
b0 #
b1000 "
#2580
b1001 $
1)
1!
#2590
1(
0!
b1 #
#2600
1.
1+
b1010 $
0)
b1 %
1*
1!
#2610
03
00
0+
b1010 $
1.
0/
b0 %
0*
0(
1-
0!
b10 #
#2620
b1011 $
1)
1!
#2630
1(
0!
b11 #
#2640
13
10
0.
1/
1+
b1100 $
0)
b11 %
1*
1!
#2650
18
0&
00
05
0+
0.
0/
b1100 $
13
04
b0 %
0*
0(
0-
12
0!
b100 #
#2660
b1101 $
1)
1!
#2670
1(
0!
b101 #
#2680
1.
1+
b1110 $
0)
b1 %
1*
1!
#2690
18
0&
05
13
04
00
0+
b1110 $
1.
0/
b0 %
0*
0(
1-
0!
b110 #
#2700
b1111 $
1)
1!
#2710
1(
0!
b111 #
#2720
08
1&
15
03
14
10
0.
1/
1+
b0 $
0)
b111 %
1*
1!
#2730
00
05
0+
0.
0/
03
04
b0 $
08
b0 %
0*
0(
0-
02
17
0!
b1000 #
#2740
b1 $
1)
1!
#2750
1(
0!
b1001 #
#2760
1.
1+
b10 $
0)
b1 %
1*
1!
#2770
03
00
0+
b10 $
1.
0/
b0 %
0*
0(
1-
0!
b1010 #
#2780
b11 $
1)
1!
#2790
1(
0!
b1011 #
#2800
13
10
0.
1/
1+
b100 $
0)
b11 %
1*
1!
#2810
08
00
05
0+
0.
0/
b100 $
13
04
b0 %
0*
0(
0-
12
0!
b1100 #
#2820
b101 $
1)
1!
#2830
1(
0!
b1101 #
#2840
1.
1+
b110 $
0)
b1 %
1*
1!
#2850
08
05
13
04
00
0+
b110 $
1.
0/
b0 %
0*
0(
1-
0!
b1110 #
#2860
b111 $
1)
1!
#2870
1(
0!
b1111 #
#2880
18
15
03
14
10
0.
1/
1+
b1000 $
0)
b111 %
1*
1!
#2890
0&
00
05
0+
0.
0/
03
04
18
b1001 $
1)
b0 %
0*
0(
0-
02
07
1'
0!
b0 #
b1001 "
#2900
1.
1+
b1010 $
0)
b1 %
1*
1!
#2910
1(
0!
b1 #
#2920
b1011 $
1)
1!
#2930
03
0+
00
0*
b1011 $
1.
b0 %
0/
0(
1-
0!
b10 #
#2940
13
10
0.
1/
1+
b1100 $
0)
b11 %
1*
1!
#2950
1(
0!
b11 #
#2960
b1101 $
1)
1!
#2970
18
0&
0+
00
05
0*
0.
0/
b1101 $
13
b0 %
04
0(
0-
12
0!
b100 #
#2980
1.
1+
b1110 $
0)
b1 %
1*
1!
#2990
1(
0!
b101 #
#3000
b1111 $
1)
1!
#3010
18
0&
05
13
04
0+
00
0*
b1111 $
1.
b0 %
0/
0(
1-
0!
b110 #
#3020
08
1&
15
03
14
10
0.
1/
1+
b0 $
0)
b111 %
1*
1!
#3030
1(
0!
b111 #
#3040
b1 $
1)
1!
#3050
0+
00
05
0*
0.
0/
03
b0 %
04
b1 $
08
0(
0-
02
17
0!
b1000 #
#3060
1.
1+
b10 $
0)
b1 %
1*
1!
#3070
1(
0!
b1001 #
#3080
b11 $
1)
1!
#3090
03
0+
00
0*
b11 $
1.
b0 %
0/
0(
1-
0!
b1010 #
#3100
13
10
0.
1/
1+
b100 $
0)
b11 %
1*
1!
#3110
1(
0!
b1011 #
#3120
b101 $
1)
1!
#3130
08
0+
00
05
0*
0.
0/
b101 $
13
b0 %
04
0(
0-
12
0!
b1100 #
#3140
1.
1+
b110 $
0)
b1 %
1*
1!
#3150
1(
0!
b1101 #
#3160
b111 $
1)
1!
#3170
08
05
13
04
0+
00
0*
b111 $
1.
b0 %
0/
0(
1-
0!
b1110 #
#3180
18
15
03
14
10
0.
1/
1+
b1000 $
0)
b111 %
1*
1!
#3190
1(
0!
b1111 #
#3200
b1001 $
1)
1!
#3210
00
0&
1.
0/
05
0+
03
04
18
b0 %
0*
b1010 $
0)
0(
0-
02
07
0'
1,
0!
b0 #
b1010 "
#3220
b1011 $
1)
1!
#3230
1(
0!
b1 #
#3240
13
10
0.
1/
1+
b1100 $
0)
b11 %
1*
1!
#3250
0+
b1100 $
0.
b10 %
0*
0(
1-
0!
b10 #
#3260
b1101 $
1)
1!
#3270
1(
0!
b11 #
#3280
1.
1+
b1110 $
0)
b11 %
1*
1!
#3290
00
18
0&
0/
05
0+
1.
b1110 $
13
04
b0 %
0*
0(
0-
12
0!
b100 #
#3300
b1111 $
1)
1!
#3310
1(
0!
b101 #
#3320
08
1&
15
03
14
10
0.
1/
1+
b0 $
0)
b111 %
1*
1!
#3330
0+
b0 $
0.
b110 %
0*
0(
1-
0!
b110 #
#3340
b1 $
1)
1!
#3350
1(
0!
b111 #
#3360
1.
1+
b10 $
0)
b111 %
1*
1!
#3370
00
0/
05
0+
1.
03
04
b10 $
08
b0 %
0*
0(
0-
02
17
0!
b1000 #
#3380
b11 $
1)
1!
#3390
1(
0!
b1001 #
#3400
13
10
0.
1/
1+
b100 $
0)
b11 %
1*
1!
#3410
0+
b100 $
0.
b10 %
0*
0(
1-
0!
b1010 #
#3420
b101 $
1)
1!
#3430
1(
0!
b1011 #
#3440
1.
1+
b110 $
0)
b11 %
1*
1!
#3450
00
08
0/
05
0+
1.
b110 $
13
04
b0 %
0*
0(
0-
12
0!
b1100 #
#3460
b111 $
1)
1!
#3470
1(
0!
b1101 #
#3480
18
15
03
14
10
0.
1/
1+
b1000 $
0)
b111 %
1*
1!
#3490
0+
b1000 $
0.
b110 %
0*
0(
1-
0!
b1110 #
#3500
b1001 $
1)
1!
#3510
1(
0!
b1111 #
#3520
1.
1+
b1010 $
0)
b111 %
1*
1!
#3530
00
0&
0/
05
0+
1.
03
04
18
b1011 $
1)
b0 %
0*
0(
0-
02
07
1'
0!
b0 #
b1011 "
#3540
13
10
0.
1/
1+
b1100 $
0)
b11 %
1*
1!
#3550
1(
0!
b1 #
#3560
b1101 $
1)
1!
#3570
0+
b10 %
0*
b1101 $
0.
0(
1-
0!
b10 #
#3580
1.
1+
b1110 $
0)
b11 %
1*
1!
#3590
1(
0!
b11 #
#3600
b1111 $
1)
1!
#3610
00
0/
18
0&
0+
05
0*
1.
b1111 $
13
b0 %
04
0(
0-
12
0!
b100 #
#3620
08
1&
15
03
14
10
0.
1/
1+
b0 $
0)
b111 %
1*
1!
#3630
1(
0!
b101 #
#3640
b1 $
1)
1!
#3650
0+
b110 %
0*
b1 $
0.
0(
1-
0!
b110 #
#3660
1.
1+
b10 $
0)
b111 %
1*
1!
#3670
1(
0!
b111 #
#3680
b11 $
1)
1!
#3690
00
0/
0+
05
0*
1.
03
b0 %
04
b11 $
08
0(
0-
02
17
0!
b1000 #
#3700
13
10
0.
1/
1+
b100 $
0)
b11 %
1*
1!
#3710
1(
0!
b1001 #
#3720
b101 $
1)
1!
#3730
0+
b10 %
0*
b101 $
0.
0(
1-
0!
b1010 #
#3740
1.
1+
b110 $
0)
b11 %
1*
1!
#3750
1(
0!
b1011 #
#3760
b111 $
1)
1!
#3770
00
0/
08
0+
05
0*
1.
b111 $
13
b0 %
04
0(
0-
12
0!
b1100 #
#3780
18
15
03
14
10
0.
1/
1+
b1000 $
0)
b111 %
1*
1!
#3790
1(
0!
b1101 #
#3800
b1001 $
1)
1!
#3810
0+
b110 %
0*
b1001 $
0.
0(
1-
0!
b1110 #
#3820
1.
1+
b1010 $
0)
b111 %
1*
1!
#3830
1(
0!
b1111 #
#3840
b1011 $
1)
1!
#3850
0&
05
13
04
0.
00
0+
0/
18
b0 %
0*
b1100 $
0)
0(
0-
02
07
0'
0,
11
0!
b0 #
b1100 "
#3860
b1101 $
1)
1!
#3870
1(
0!
b1 #
#3880
1.
1+
b1110 $
0)
b1 %
1*
1!
#3890
18
0&
05
13
04
00
0+
b1110 $
1.
0/
b0 %
0*
0(
1-
0!
b10 #
#3900
b1111 $
1)
1!
#3910
1(
0!
b11 #
#3920
08
1&
15
03
14
10
0.
1/
1+
b0 $
0)
b111 %
1*
1!
#3930
00
0+
0.
0/
b0 $
03
b100 %
0*
0(
0-
12
0!
b100 #
#3940
b1 $
1)
1!
#3950
1(
0!
b101 #
#3960
1.
1+
b10 $
0)
b101 %
1*
1!
#3970
03
00
0+
b10 $
1.
0/
b100 %
0*
0(
1-
0!
b110 #
#3980
b11 $
1)
1!
#3990
1(
0!
b111 #
#4000
13
10
0.
1/
1+
b100 $
0)
b111 %
1*
1!
#4010
05
04
00
0+
0.
0/
13
b100 $
08
b0 %
0*
0(
0-
02
17
0!
b1000 #
#4020
b101 $
1)
1!
#4030
1(
0!
b1001 #
#4040
1.
1+
b110 $
0)
b1 %
1*
1!
#4050
08
05
13
04
00
0+
b110 $
1.
0/
b0 %
0*
0(
1-
0!
b1010 #
#4060
b111 $
1)
1!
#4070
1(
0!
b1011 #
#4080
18
15
03
14
10
0.
1/
1+
b1000 $
0)
b111 %
1*
1!
#4090
00
0+
0.
0/
b1000 $
03
b100 %
0*
0(
0-
12
0!
b1100 #
#4100
b1001 $
1)
1!
#4110
1(
0!
b1101 #
#4120
1.
1+
b1010 $
0)
b101 %
1*
1!
#4130
03
00
0+
b1010 $
1.
0/
b100 %
0*
0(
1-
0!
b1110 #
#4140
b1011 $
1)
1!
#4150
1(
0!
b1111 #
#4160
13
10
0.
1/
1+
b1100 $
0)
b111 %
1*
1!
#4170
0&
05
04
00
0+
0.
0/
13
18
b1101 $
1)
b0 %
0*
0(
0-
02
07
1'
0!
b0 #
b1101 "
#4180
1.
1+
b1110 $
0)
b1 %
1*
1!
#4190
1(
0!
b1 #
#4200
b1111 $
1)
1!
#4210
18
0&
05
13
04
0+
00
0*
b1111 $
1.
b0 %
0/
0(
1-
0!
b10 #
#4220
08
1&
15
03
14
10
0.
1/
1+
b0 $
0)
b111 %
1*
1!
#4230
1(
0!
b11 #
#4240
b1 $
1)
1!
#4250
0+
00
0*
0.
b100 %
0/
b1 $
03
0(
0-
12
0!
b100 #
#4260
1.
1+
b10 $
0)
b101 %
1*
1!
#4270
1(
0!
b101 #
#4280
b11 $
1)
1!
#4290
03
0+
00
0*
b11 $
1.
b100 %
0/
0(
1-
0!
b110 #
#4300
13
10
0.
1/
1+
b100 $
0)
b111 %
1*
1!
#4310
1(
0!
b111 #
#4320
b101 $
1)
1!
#4330
05
04
0+
00
0*
0.
b0 %
0/
13
b101 $
08
0(
0-
02
17
0!
b1000 #
#4340
1.
1+
b110 $
0)
b1 %
1*
1!
#4350
1(
0!
b1001 #
#4360
b111 $
1)
1!
#4370
08
05
13
04
0+
00
0*
b111 $
1.
b0 %
0/
0(
1-
0!
b1010 #
#4380
18
15
03
14
10
0.
1/
1+
b1000 $
0)
b111 %
1*
1!
#4390
1(
0!
b1011 #
#4400
b1001 $
1)
1!
#4410
0+
00
0*
0.
b100 %
0/
b1001 $
03
0(
0-
12
0!
b1100 #
#4420
1.
1+
b1010 $
0)
b101 %
1*
1!
#4430
1(
0!
b1101 #
#4440
b1011 $
1)
1!
#4450
03
0+
00
0*
b1011 $
1.
b100 %
0/
0(
1-
0!
b1110 #
#4460
13
10
0.
1/
1+
b1100 $
0)
b111 %
1*
1!
#4470
1(
0!
b1111 #
#4480
b1101 $
1)
1!
#4490
0&
05
04
00
1.
0/
0+
13
18
b0 %
0*
b1110 $
0)
0(
0-
02
07
0'
1,
0!
b0 #
b1110 "
#4500
b1111 $
1)
1!
#4510
1(
0!
b1 #
#4520
08
1&
15
03
14
10
0.
1/
1+
b0 $
0)
b111 %
1*
1!
#4530
0+
b0 $
0.
b110 %
0*
0(
1-
0!
b10 #
#4540
b1 $
1)
1!
#4550
1(
0!
b11 #
#4560
1.
1+
b10 $
0)
b111 %
1*
1!
#4570
00
0/
0+
1.
b10 $
03
b100 %
0*
0(
0-
12
0!
b100 #
#4580
b11 $
1)
1!
#4590
1(
0!
b101 #
#4600
13
10
0.
1/
1+
b100 $
0)
b111 %
1*
1!
#4610
0+
b100 $
0.
b110 %
0*
0(
1-
0!
b110 #
#4620
b101 $
1)
1!
#4630
1(
0!
b111 #
#4640
1.
1+
b110 $
0)
b111 %
1*
1!
#4650
05
04
00
0/
0+
1.
13
b110 $
08
b0 %
0*
0(
0-
02
17
0!
b1000 #
#4660
b111 $
1)
1!
#4670
1(
0!
b1001 #
#4680
18
15
03
14
10
0.
1/
1+
b1000 $
0)
b111 %
1*
1!
#4690
0+
b1000 $
0.
b110 %
0*
0(
1-
0!
b1010 #
#4700
b1001 $
1)
1!
#4710
1(
0!
b1011 #
